hstu_attn_2_cuda.cpython-310-x86_64-linux-gnu.so
hstu_attn/__init__.py
hstu_attn/hstu_attn_interface.py
hstu_attn/hstu_utils.py
hstu_attn/triton_ragged_hstu_attention.py
hstu_attn-1.3.dist-info/METADATA
hstu_attn-1.3.dist-info/WHEEL
hstu_attn-1.3.dist-info/top_level.txt
hstu_attn-1.3.dist-info/RECORD
