Metadata-Version: 2.1
Name: hstu-attn
Version: 1.3
Summary: HSTU Attention: The HSTU structure mainly serves generative recommendation
Home-page: https://github.com/Dao-AILab/flash-attention
Author: binc & alex
Author-email: binc@nvidia.com
License: UNKNOWN
Platform: UNKNOWN
Classifier: Programming Language :: Python :: 3
Classifier: License :: OSI Approved :: BSD License
Classifier: Operating System :: Unix
Requires-Python: >=3.7
Requires-Dist: torch
Requires-Dist: einops
